{
  "schedule_meeting": 0,
  "where_are_you_from": 1,
  "vaccines": 2,
  "transfer": 3,
  "carry_on": 4,
  "weather": 5,
  "next_holiday": 6,
  "travel_alert": 7,
  "pin_change": 8,
  "credit_score": 9,
  "calories": 10,
  "pay_bill": 11,
  "what_is_your_name": 12,
  "spelling": 13,
  "timezone": 14,
  "reset_settings": 15,
  "shopping_list_update": 16,
  "order_status": 17,
  "what_can_i_ask_you": 18,
  "travel_suggestion": 19,
  "oil_change_how": 20,
  "definition": 21,
  "nutrition_info": 22,
  "income": 23,
  "what_are_your_hobbies": 24,
  "meeting_schedule": 25,
  "ingredient_substitution": 26,
  "how_busy": 27,
  "directions": 28,
  "last_maintenance": 29,
  "accept_reservations": 30,
  "current_location": 31,
  "report_lost_card": 32,
  "balance": 33,
  "min_payment": 34,
  "food_last": 35,
  "expiration_date": 36,
  "translate": 37,
  "restaurant_suggestion": 38,
  "make_call": 39,
  "play_music": 40,
  "greeting": 41,
  "reminder_update": 42,
  "confirm_reservation": 43,
  "gas_type": 44,
  "no": 45,
  "application_status": 46,
  "interest_rate": 47,
  "apr": 48,
  "who_do_you_work_for": 49,
  "tire_change": 50,
  "timer": 51,
  "next_song": 52,
  "cancel_reservation": 53,
  "change_ai_name": 54,
  "distance": 55,
  "oil_change_when": 56,
  "pto_used": 57,
  "pto_request": 58,
  "cancel": 59,
  "user_name": 60,
  "report_fraud": 61,
  "routing": 62,
  "lost_luggage": 63,
  "damaged_card": 64,
  "uber": 65,
  "maybe": 66,
  "meaning_of_life": 67,
  "smart_home": 68,
  "plug_type": 69,
  "calendar_update": 70,
  "replacement_card_duration": 71,
  "goodbye": 72,
  "international_fees": 73,
  "update_playlist": 74,
  "exchange_rate": 75,
  "schedule_maintenance": 76,
  "yes": 77,
  "todo_list_update": 78,
  "card_declined": 79,
  "time": 80,
  "order": 81,
  "calendar": 82,
  "ingredients_list": 83,
  "traffic": 84,
  "bill_balance": 85,
  "change_volume": 86,
  "cook_time": 87,
  "pto_balance": 88,
  "roll_dice": 89,
  "order_checks": 90,
  "travel_notification": 91,
  "credit_limit_change": 92,
  "change_speed": 93,
  "taxes": 94,
  "account_blocked": 95,
  "w2": 96,
  "rollover_401k": 97,
  "calculator": 98,
  "mpg": 99,
  "reminder": 100,
  "credit_limit": 101,
  "meal_suggestion": 102,
  "sync_device": 103,
  "restaurant_reservation": 104,
  "repeat": 105,
  "tell_joke": 106,
  "rewards_balance": 107,
  "share_location": 108,
  "change_language": 109,
  "international_visa": 110,
  "improve_credit_score": 111,
  "find_phone": 112,
  "bill_due": 113,
  "payday": 114,
  "jump_start": 115,
  "thank_you": 116,
  "flight_status": 117,
  "measurement_conversion": 118,
  "insurance_change": 119,
  "redeem_rewards": 120,
  "tire_pressure": 121,
  "todo_list": 122,
  "new_card": 123,
  "change_accent": 124,
  "do_you_have_pets": 125,
  "alarm": 126,
  "book_flight": 127,
  "car_rental": 128,
  "text": 129,
  "gas": 130,
  "recipe": 131,
  "pto_request_status": 132,
  "direct_deposit": 133,
  "are_you_a_bot": 134,
  "who_made_you": 135,
  "spending_history": 136,
  "restaurant_reviews": 137,
  "freeze_account": 138,
  "how_old_are_you": 139,
  "whisper_mode": 140,
  "shopping_list": 141,
  "change_user_name": 142,
  "date": 143,
  "insurance": 144,
  "book_hotel": 145,
  "fun_fact": 146,
  "flip_coin": 147,
  "transactions": 148,
  "what_song": 149
}